{
    "titre":  "Meilleurs baguettes de Paris",
    "tous":  "Tous",
    "About":  "Qu\u0027est ce que c\u0027est",
    "goalContent":  "Ce site repertorie les 10 premiers laureats et le gagnant de chaque annee du ",
    "contestwikipedia":  "concours de la meilleure baguette de Paris",
    "goalContentEnd":  "de ses debuts (1994) a aujourd\u0027hui (2023).",
    "sources":  "Sources",
    "ranking":  "Seuls les classements a partir de l\u0027annee 2010 sont trouvables en ligne, il n\u0027existe pas d\u0027archives accessibles publiquement.",
    "rankingByYear":  "Ci-dessous la liste des sources pour chaque annee.",
    "helpWelcome":  "Toute aide est la bienvenue si vous disposez de sources pour les annees anterieures. Envoyez moi un e-mail a",
    "sourceCode":  "code source",
    "writeMe":  "Vous pouvez m\u0027ecrire directement a",
    "sourceCodeAvailable":  "Le code source est disponible",
    "ici":  "ici",
    "divers":  "Divers",
    "displayGold":  "Afficher seulement les premiers prix",
    "displaySilver":  "Afficher seulement les seconds prix",
    "displayThird":  "Afficher les troisiemes",
    "displayAll":  "Tout afficher (defaut)",
    "introPatteFolle":  "Si vous aimez faire du pain, il existe aussi cette application que j\u0027ai ",
    "app":  "developpee",
    "anymore":  "N\u0027existe plus",
    "noBakery":  "Il n\u0027y a pas de boulangeries sur cette surface. Deplacer la fenetre ou dezoomer pour en trouver une.",
    "adHeadline":  "Parce que l\u0027art aussi se deguste",
    "adTagline":  "Decouvrez mes t-shirts voyageurs.",
    "adCta":  "Voir la boutique"
}
